Workbook
Name anos: 'App Meus FIIs'!$F$22
Name Meu_Salario: 'App Meus FIIs'!$E$15
Name patrimonio: 'App Meus FIIs'!$F$24
Name rendimentodacarteira: 'App Meus FIIs'!$E$16
Name Suges_invest: 'App Meus FIIs'!$E$17
Name tax_rend_mes: 'App Meus FIIs'!$F$23
Name valor_aportado: 'App Meus FIIs'!$F$21

Sheet App Meus FIIs
B14: Vamos começar por aqui!
B15: Meu salário: | E15: 20000
B16: Rendimento da Carteira: | E16: 0.0099
B17: Sugestão de Investimento: | E17: =E15*30% -> 6000
B20: Calculadora de Investimento Mensal
B21: Se eu investir todo mês: | F21: 6500
B22: Pelo período de (anos): | F22: 2
B23: Com uma taxa de rendimento mensal de: | F23: 0.01079
B24: Ao final de todos estes anos terei: | F24: =FV(tax_rend_mes,anos*12,valor_aportado*-1) -> 176979.58
B25: E todo mês vou ganhar na minha conta em dividendos: | F25: =(patrimonio*rendimentodacarteira) -> 1752.0978
B27: Previsões para me animar ainda mais a investir sempre:
B28: Prazo do Investimento | E28: Patrimônio | F28: Dividendos
A29: 2 | B29: Por 2 anos: | E29: =FV($F$23,A$29*12,$F$21*-1) -> 176979.58 | F29: =E29*rendimentodacarteira -> 1752.0978
A30: 5 | B30: Por 5 anos: | E30: =FV($F$23,A$30*12,$F$21*-1) -> 544549.94 | F30: =E30*rendimentodacarteira -> 5391.0444
A31: 10 | B31: Por 10 anos: | E31: =FV($F$23,A$31*12,$F$21*-1) -> 1581347.4 | F31: =E31*rendimentodacarteira -> 15655.339
A32: 20 | B32: Por 20 anos: | E32: =FV($F$23,A32*12,F21*-1) -> 7313789.6 | F32: =E32*rendimentodacarteira -> 72406.517
A33: 30 | B33: Por 30 anos: | E33: =FV($F$23,A$33*12,$F$21*-1) -> 28094103 | F33: =E33*rendimentodacarteira -> 278131.62
B35: Distribuição dos Investimentos
B36: No teste da corretora, fui classificado como um investidor: | F36: Agressivo
B37: Total investido por mês: | F37: =valor_aportado -> 6500
B38: Tipo de FII | D38: Percentual Indicado | F38: Valor
B39: Papel | D39: =VLOOKUP($F$36&"-"&B39,Planilha2!$A:$D,4,FALSE) -> 0.5 | F39: =D39*$F$37 -> 3250
B40: Tijolo | D40: =VLOOKUP($F$36&"-"&B40,Planilha2!$A:$D,4,FALSE) -> 0.1 | F40: =D40*$F$37 -> 650
B41: Híbrido | D41: =VLOOKUP($F$36&"-"&B41,Planilha2!$A:$D,4,FALSE) -> 0.05 | F41: =D41*$F$37 -> 325
B42: FOF | D42: =VLOOKUP($F$36&"-"&B42,Planilha2!$A:$D,4,FALSE) -> 0.05 | F42: =D42*$F$37 -> 325
B43: Desenvolvimento | D43: =VLOOKUP($F$36&"-"&B43,Planilha2!$A:$D,4,FALSE) -> 0.2 | F43: =D43*$F$37 -> 1300
B44: Hotelaria | D44: =VLOOKUP($F$36&"-"&B44,Planilha2!$A:$D,4,FALSE) -> 0.1 | F44: =D44*$F$37 -> 650
B45: Total | F45: =SUM(F39:F44) -> 6500

Sheet Planilha2
A1: Chave | B1: Perfil | C1: Categoria de FII | D1: Porcentagem
A2: =B2&"-"&C2 -> Conservador-Papel | B2: Conservador | C2: Papel | D2: 0.3
A3: =B3&"-"&C3 -> Conservador-Tijolo | B3: Conservador | C3: Tijolo | D3: 0.5
A4: =B4&"-"&C4 -> Conservador-Híbrido | B4: Conservador | C4: Híbrido | D4: 0.1
A5: =B5&"-"&C5 -> Conservador-FOF | B5: Conservador | C5: FOF | D5: 0.1
A6: =B6&"-"&C6 -> Conservador-Desenvolvimento | B6: Conservador | C6: Desenvolvimento | D6: 0
A7: =B7&"-"&C7 -> Conservador-Hotelaria | B7: Conservador | C7: Hotelaria | D7: 0
A8: =B8&"-"&C8 -> Moderado-Papel | B8: Moderado | C8: Papel | D8: 0.32
A9: =B9&"-"&C9 -> Moderado-Tijolo | B9: Moderado | C9: Tijolo | D9: 0.35
A10: =B10&"-"&C10 -> Moderado-Híbrido | B10: Moderado | C10: Híbrido | D10: 0.08
A11: =B11&"-"&C11 -> Moderado-FOF | B11: Moderado | C11: FOF | D11: 0.05
A12: =B12&"-"&C12 -> Moderado-Desenvolvimento | B12: Moderado | C12: Desenvolvimento | D12: 0.1
A13: =B13&"-"&C13 -> Moderado-Hotelaria | B13: Moderado | C13: Hotelaria | D13: 0.1
... A19: =B19&"-"&C19 -> Agressivo-Hotelaria | B19: Agressivo | C19: Hotelaria | D19: 0.1
